{
  "id": "work",
  "title": "仕事と社会での立ち回り",
  "osLabel": "社会OS",
  "description": "組織・評価・お金の構造を理解し、現実的に立ち回るための処世術。",
  "topics": [
    {
      "id": "work-expected-value",
      "title": "『期待値』で動くと、感情に振り回されにくい",
      "summary": "好き嫌いだけでなく、リターンとコストの期待値で考える視点を持つ。",
      "essence": [
        "仕事は多くが“確実な結果”ではなく“期待値ベースの賭け”である。",
        "短期の感情ではなく長期の期待値で動く方が消耗しにくい。",
        "期待値思考は『今ここで頑張る意味』を言葉にする作業でもある。"
      ],
      "traps": [
        "『努力すれば報われる』思考だけで突っ走る。",
        "やりがいだけで仕事を選び、生活が崩れて後悔する。",
        "逆にお金だけに寄りすぎて、長期的な幸福を削る。"
      ],
      "actionTips": [
        "今の仕事を『経験・お金・人脈・スキル』で10点評価してみる。",
        "点数が低い領域は“手放すか改善するか”を検討する。",
        "新しい仕事は『1年後の自分』をイメージして評価する。"
      ],
      "tags": ["キャリア", "お金", "期待値", "仕事選び"]
    },
    {
      "id": "work-boss-handle",
      "title": "上司は『攻略対象』として扱うと楽になる",
      "summary": "好き嫌いではなく“どう扱えばスムーズか”に注力する。",
      "essence": [
        "上司も不完全な人間であり、万能ではない。",
        "相手の“こだわりポイント”を把握すると仕事が早く進む。",
        "評価の取り方は心理戦ではなく“観察”に近い。"
      ],
      "traps": [
        "上司の粗探しばかりして自分の行動を改善しない。",
        "尊敬できない＝働けない、の短絡思考に陥る。",
        "諦めて提案しなくなり、機会損失が大きくなる。"
      ],
      "actionTips": [
        "上司がよく使うキーワードを3つメモし資料に盛り込む。",
        "曖昧な指示には『AとBならどちらが好みですか？』と選択肢質問をする。",
        "合わない場合は“学びを回収したら離れる”前提で受け流す。"
      ],
      "tags": ["組織攻略", "社会OS", "上司対応", "会社員スキル"]
    },
    {
      "id": "work-side-bet",
      "title": "本業一本より『小さなサイドベット』が心を守る",
      "summary": "副業は金額以上に“心の逃げ道”として機能する。",
      "essence": [
        "収入・承認欲求を一社に依存すると不安定になりがち。",
        "自分の裁量で動かせる活動が1つあるだけで気持ちが安定する。",
        "サイドベットは“大きくする”より“細く長く続ける”方が重要。"
      ],
      "traps": [
        "本業も副業も全力で燃え尽きる。",
        "規定を無視して副業し信用を失う。",
        "収益化を焦って楽しさを消してしまう。"
      ],
      "actionTips": [
        "月1時間からできる“小さな実験”を始める。",
        "本業と相性が良いスキルを選び、相乗効果を狙う。",
        "収益ゼロでも“苦にならない活動か”で選ぶ。"
      ],
      "tags": ["キャリア", "副業", "働き方", "リスク分散"]
    }
  ]
}
